<?xml version="1.0" encoding="UTF-8"?>
<mods xmlns:mods="http://www.loc.gov/mods/v3"
      xmlns:xlink="http://www.w3.org/1999/xlink"
      xmlns:xsi="http://www.w3.org/2001/XMLSchema-instance"
      xmlns="http://www.loc.gov/mods/v3">
   <titleInfo>
      <title>Page 120</title>
  </titleInfo>
   <relatedItem type="host">
      <location>
         <url displayLabel="Relation">http://louisianadigitallibrary.org/islandora/object/lsu-sc-p15140coll10:collection</url>
      </location>
  </relatedItem>
   <location>
      <physicalLocation displayLabel="Physical Location" xlink:href="http://lib.lsu.edu">LSU Libraries</physicalLocation>
      <physicalLocation authority="oclcorg" displayLabel="OCLC Member Symbol">LUU</physicalLocation>
      
   </location>
   <identifier displayLabel="Migrated From" invalid="yes" type="uri">http://cdm16313.contentdm.oclc.org/cdm/singleitem/collection/p15140coll10/id/1604</identifier>
   <recordInfo>
      <recordOrigin>Transformed into MODS from extended Dublin Core by the LDL Development Team at Louisiana State University.</recordOrigin>
      <recordCreationDate>2012-01-18</recordCreationDate>
      <recordChangeDate>2018-12-05-06:00</recordChangeDate>
      <languageOfCataloging>
         <languageTerm type="code" authority="iso639-2b">eng</languageTerm>
      </languageOfCataloging>
   </recordInfo>
   <extension>
      <CONTENTdmData>
         <alias>p15140coll10</alias>
         <pointer>1604</pointer>
         <dmGetItemInfo mimetype="application/json"
                        source="https://server16313.contentdm.oclc.org/dmwebservices/index.php?q=dmGetItemInfo/p15140coll10/1604/json"
                        timestamp="2017-02-03 08:23:13">{"title":"Page 120","subjec":{},"descri":{},"creato":{},"publis":{},"date":{},"year":{},"format":{},"reposi":{},"collec":{},"reposa":{},"rights":{},"digitb":{},"langua":{},"topics":{},"cite":{},"notes":{},"notesa":{},"source":{},"box":{},"folder":{},"identi":{},"relati":{},"findin":{},"catalo":{},"type":{},"full":"\u2014 i'2tr \u2014\ndont il allait dduouer la ccinture, il avait donnd les memes signes\nd'inquidtude et de terretir.\nCe jeune homme, sombre, frissonnant, comme lady Macbeth devant le spectre dc Banco, c'dtait Hutin, nil des truands qui rava-\ngeaient Saint-Martinville, qui devait, quelques jours apres. etre la\ncause de la premiere grande prise d'armes des Comites de Vigilance.\nXXIV.-\nUn ou deux mois avant cette expulsion dramatique, un crime\nmystdrieux avait agitd la communatttd.\nQui ne connalt la eharmante fable de Lafontaine qui finit par les\nvers suivants :\nTout petit prince a deoftinlKiasadeura,\nTout marquis veut avoir des pages ?\nSaint-Martinville voulut singer les pei-sonnages de Lafontaine, !ft\njour ou deux petites rues rayonnerent, de sa place de la Maison de\ni-our, snr le chemin de la Nouvelle-Iberie. De ces rues ses alder-\nmeu firent un faisceau qu'ils appelerent\/at^oio-g.\nParis a Hes faubourgs d'une certaine etendue; la Nouvelle-Grldans\nen compte aussi quclques-uns.\u2014Pourquoi Saint-Martinville n'au-\nrait il pas eu les siens ?\nDans une heure de pvodigalitd,\u2014prodigalitd d'autant plus lacile\nqu'elle ne coutait rien a leur bourse, ses aldermen lui en donnerent\ndeux : un vrai et un bien rdellcment faux {ceci soit dit sans jeu de\nmots).\nLe vrai, c'est celui qui s'etend de l'autre cotd du pont, comme un\nIdzard au soleil du bon Dieu, et dont la rue ressemble plutot ii nn\nravin effondre\" par des pluies torrentielles qu'a un lieu de passage\npour les cavaliers et les riches demipages de la Pointe et de la\nFausse-Pointe qui se rendent a Saint-Martin. Sahara1'dtd, mer de\nboue 1'hiver, cette rue est la voie des douleurs. via dolorosa.; celle\nqui a vu et voit encore passer tant de dcuils aceempagnant ecus\nqui s'en vont an cimetiere.\nLe vrai faubourg est celui de Pineauvillc.\nLe faux est celui que les topographes de Saint-Martinville ont\ntailld  daus les deux ou trois ruellcs qui, partant de la Maison da","fullrs":{},"find":"1605.jp2","dmaccess":{},"dmimage":{},"dmcreated":"2012-01-18","dmmodified":"2012-01-18","dmoclcno":{},"dmrecord":"1604","restrictionCode":"1","cdmfilesize":"424089","cdmfilesizeformatted":"0.40 MB","cdmprintpdf":"0","cdmhasocr":"1","cdmisnewspaper":"0"}</dmGetItemInfo>
      </CONTENTdmData>
  </extension>
</mods>
